{"chrome://browser/content/browser.xul":{"navigator-toolbox":{"iconsize":"small"},"main-window":{"screenX":"0","screenY":"40","width":"1085","height":"803","sizemode":"maximized"},"urlbar-container":{"width":"784"},"search-container":{"width":"267"},"sidebar-box":{"sidebarcommand":"","width":"","src":""}},"chrome://mozapps/content/downloads/unknownContentType.xul":{"unknownContentType":{"screenX":"596","screenY":"343"}},"chrome://browser/content/pageinfo/pageInfo.xul":{"main-window":{"screenX":"998","screenY":"325","width":"600","height":"550","sizemode":"normal"}}}